gerberex/__init__.py
gerberex/am_expression.py
gerberex/am_primitive.py
gerberex/common.py
gerberex/composition.py
gerberex/dxf.py
gerberex/dxf_path.py
gerberex/excellon.py
gerberex/gerber_statements.py
gerberex/rs274x.py
gerberex/utility.py
pcb_tools_extension-0.9.3.dist-info/LICENSE
pcb_tools_extension-0.9.3.dist-info/METADATA
pcb_tools_extension-0.9.3.dist-info/WHEEL
pcb_tools_extension-0.9.3.dist-info/top_level.txt
pcb_tools_extension-0.9.3.dist-info/RECORD
