Metadata-Version: 2.1
Name: pcb-tools-extension
Version: 0.9.3
Summary: Extension for pcb-tools package to panelize gerber files
Home-page: http://github.com/opiopan/pcb-tools-extension
Author: Hiroshi Murayama <opiopan@gmail.com>
Author-email: opiopan@gmail.com
License: Apache
Keywords: pcb gerber tools extension
Platform: UNKNOWN
Classifier: Development Status :: 4 - Beta
Classifier: Topic :: Utilities
Classifier: License :: OSI Approved :: Apache Software License
Classifier: Programming Language :: Python :: 3
Classifier: Programming Language :: Python :: 3.3
Classifier: Programming Language :: Python :: 3.4
Classifier: Programming Language :: Python :: 3.5
Classifier: Programming Language :: Python :: 3.6
Classifier: Programming Language :: Python :: 3.7
Classifier: Programming Language :: Python :: 3.8
Requires-Dist: pcb-tools
Requires-Dist: dxfgrabber
